napari_himena/__init__.py
napari_himena/_widget.py
napari_himena/himena_commands.py
napari_himena/napari.yaml
napari_himena/_tests/__init__.py
napari_himena/_tests/test_himena_commands.py
napari_himena-0.0.1.dist-info/licenses/LICENSE
napari_himena-0.0.1.dist-info/METADATA
napari_himena-0.0.1.dist-info/WHEEL
napari_himena-0.0.1.dist-info/entry_points.txt
napari_himena-0.0.1.dist-info/top_level.txt
napari_himena-0.0.1.dist-info/RECORD
