Metadata-Version: 2.4
Name: napari-himena
Version: 0.0.1
Summary: Pipeline between napari and himena
Author: Hanjin Liu
Author-email: liuhanjin.sc@gmail.com
License: 
Project-URL: Bug Tracker, https://github.com/hanjinliu/napari-himena/issues
Project-URL: Documentation, https://github.com/hanjinliu/napari-himena#README.md
Project-URL: Source Code, https://github.com/hanjinliu/napari-himena
Project-URL: User Support, https://github.com/hanjinliu/napari-himena/issues
Classifier: Development Status :: 2 - Pre-Alpha
Classifier: Framework :: napari
Classifier: Intended Audience :: Developers
Classifier: License :: OSI Approved :: BSD License
Classifier: Operating System :: OS Independent
Classifier: Programming Language :: Python
Classifier: Programming Language :: Python :: 3
Classifier: Programming Language :: Python :: 3 :: Only
Classifier: Programming Language :: Python :: 3.10
Classifier: Programming Language :: Python :: 3.11
Classifier: Programming Language :: Python :: 3.12
Classifier: Programming Language :: Python :: 3.13
Classifier: Topic :: Scientific/Engineering :: Image Processing
Requires-Python: >=3.10
License-File: LICENSE
Requires-Dist: himena
Provides-Extra: testing
Requires-Dist: tox; extra == "testing"
Requires-Dist: pytest; extra == "testing"
Requires-Dist: pytest-cov; extra == "testing"
Requires-Dist: pytest-qt; extra == "testing"
Requires-Dist: napari; extra == "testing"
Requires-Dist: pyqt6; extra == "testing"
Dynamic: license-file
